tests/__init__.py
tests/test_climatology.py
tests/test_download.py
tests/test_download_cimis.py
tests/test_error_detect.py
tests/test_filter.py
tests/test_filter3.py
tests/test_filter4.py
tests/test_gap.py
tests/test_godin.py
tests/test_lag.py
tests/test_medianAD.py
tests/test_read_ts.py
tests/test_write_ts.py
vtools/__init__.py
vtools/_version.py
vtools/data/__init__.py
vtools/data/gap.py
vtools/data/sample_series.py
vtools/data/timeseries.py
vtools/data/vtime.py
vtools/datastore/__init__.py
vtools/datastore/read_ts.py
vtools/functions/__init__.py
vtools/functions/_monotonic_spline.py
vtools/functions/climatology.py
vtools/functions/error_detect.py
vtools/functions/example2.py
vtools/functions/filter.py
vtools/functions/frequency_response.py
vtools/functions/interannual.py
vtools/functions/interpolate.py
vtools/functions/lag_cross_correlation.py
vtools/functions/merge.py
vtools/functions/period_op.py
vtools/functions/skill_metrics.py
vtools3-3.7.3.dist-info/AUTHORS.rst
vtools3-3.7.3.dist-info/LICENSE
vtools3-3.7.3.dist-info/METADATA
vtools3-3.7.3.dist-info/WHEEL
vtools3-3.7.3.dist-info/top_level.txt
vtools3-3.7.3.dist-info/RECORD
