Metadata-Version: 2.1
Name: vtools3
Version: 3.7.3
Summary: Timeseries analysis and processing tools using pandas/xarray
Home-page: https://github.com/CADWRDeltaModeling/vtools3
Author: Eli Ateljevich
Author-email: eli@water.ca.gov
License: Apache
Keywords: vtools
Classifier: Programming Language :: Python :: 3.6
Classifier: Programming Language :: Python :: 3.7
License-File: LICENSE
License-File: AUTHORS.rst
Requires-Dist: numpy (<2,>=1.19)
Requires-Dist: pandas (>=0.23)
Requires-Dist: matplotlib
Requires-Dist: scikit-learn
Requires-Dist: scipy (>=1.2)
Requires-Dist: beautifulsoup4 (>=4.8)
Provides-Extra: docs
Requires-Dist: nbsphinx ; extra == 'docs'
Requires-Dist: sphinx-argparse ; extra == 'docs'
Requires-Dist: numpydoc ; extra == 'docs'
Provides-Extra: tests
Requires-Dist: pytest ; extra == 'tests'
